cool_linear_solver/__init__.py
cool_linear_solver/eqs_and_vars.py
cool_linear_solver/least_squares.py
cool_linear_solver/linear_programs.py
cool_linear_solver/linear_solver.py
cool_linear_solver/quadratic_problems.py
cool_linear_solver/quicksolve.py
cool_linear_solver-0.1.7.dist-info/LICENSE
cool_linear_solver-0.1.7.dist-info/METADATA
cool_linear_solver-0.1.7.dist-info/WHEEL
cool_linear_solver-0.1.7.dist-info/RECORD
