Metadata-Version: 2.1
Name: cool_linear_solver
Version: 0.1.7
Summary: An easy going (contrained) linear solver with sparse methods and minimal effort
License: BSD 3-Clause License
Author: Gerben I. Beintema
Requires-Python: >=3.10,<4.0
Classifier: License :: Other/Proprietary License
Classifier: Programming Language :: Python :: 3
Classifier: Programming Language :: Python :: 3.10
Classifier: Programming Language :: Python :: 3.11
Classifier: Programming Language :: Python :: 3.12
Classifier: Programming Language :: Python :: 3.13
Requires-Dist: cloudpickle
Requires-Dist: matplotlib
Requires-Dist: numpy (>=1.25)
Requires-Dist: qpsolvers[osqp]
